README.md
jinweilin.py
setup.py
jinwielin.egg-info/PKG-INFO
jinwielin.egg-info/SOURCES.txt
jinwielin.egg-info/dependency_links.txt
jinwielin.egg-info/top_level.txt