Metadata-Version: 2.1
Name: jinwielin
Version: 0.0.0
Summary: Python tools from Jinwei Lin Author ORCID:0000-0003-0558-6699.
Author: Jinwei Lin
Author-email: ydookey@163.com
License: UNKNOWN
Platform: UNKNOWN
